sphinx_data_viewer/__init__.py
sphinx_data_viewer/api.py
sphinx_data_viewer/assets/jsonview.bundle.css
sphinx_data_viewer/assets/jsonview.bundle.js
sphinx_data_viewer/assets/jsonview_loader.js
sphinx_data_viewer/directive.py
sphinx_data_viewer/sphinx_data_viewer.py
sphinx_data_viewer/version.py
sphinx_data_viewer-0.1.4.dist-info/LICENSE
sphinx_data_viewer-0.1.4.dist-info/METADATA
sphinx_data_viewer-0.1.4.dist-info/WHEEL
sphinx_data_viewer-0.1.4.dist-info/RECORD
